logcliasst/__init__.py
logcliasst/logcliasst.py
logcliasst-0.1.1.dist-info/LICENSE
logcliasst-0.1.1.dist-info/METADATA
logcliasst-0.1.1.dist-info/WHEEL
logcliasst-0.1.1.dist-info/top_level.txt
logcliasst-0.1.1.dist-info/RECORD
